inboxpattern/__init__.py
inboxpattern/main.py
inboxpattern/prompts.py
inboxpattern-2025.12.21181804.dist-info/METADATA
inboxpattern-2025.12.21181804.dist-info/WHEEL
inboxpattern-2025.12.21181804.dist-info/top_level.txt
inboxpattern-2025.12.21181804.dist-info/RECORD
