Metadata-Version: 2.4
Name: inboxpattern
Version: 2025.12.21181804
Summary: A new package that helps users and organizations analyze and categorize email account usage patterns. The package takes user-submitted text input describing their email management habits and returns a
Author-email: inboxpattern <hi@eugene.plus>
License: MIT
Project-URL: Homepage, https://github.com/chigwell/inboxpattern
Requires-Python: >=3.9
Requires-Dist: langchain-llm7>=0.0.0
Requires-Dist: llmatch-messages>=0.0.0
Requires-Dist: langchain-core>=0.3.0
